[
 {
  "SUMMARY": "#0182062: Service55  Bad Magic Troubleshooting w/ Admin1 ",
  "DTSTART;TZID=US/Central": "20211018T170000",
  "DTEND;TZID=US/Central": "20211018T174500",
  "DTSTAMP;VALUE=DATE-TIME": "20211018T193000Z",
  "UID": "0BB32029-839A-423C-A826-4A363B21A399",
  "SEQUENCE": "0",
  "CREATED;VALUE=DATE-TIME": "20211014T182012Z",
  "LAST-MODIFIED": "20211014T191637Z",
  "XCALNEW": "True",
  "STATUS": "CONFIRMED",
  "TRANSP": "OPAQUE",
  "X-APPLE-TRAVEL-ADVISORY-BEHAVService37 ": "AUTOMATIC",
  "XCALNAME": "0BB32029-839A-423C-A826-4A363B21A399"
 },
 {
  "SUMMARY": "#0188055: RHEL userland updates on System5  ",
  "DTSTART;TZID=US/Central": "20211018T100000",
  "DTEND;TZID=US/Central": "20211018T113000",
  "DTSTAMP;VALUE=DATE-TIME": "20211019T003000Z",
  "UID": "0C4F428B-BF4B-43DA-BEC3-510AA178728C",
  "SEQUENCE": "0",
  "CREATED;VALUE=DATE-TIME": "20211014T182012Z",
  "LAST-MODIFIED": "20211014T183034Z",
  "XCALNEW": "True",
  "STATUS": "CONFIRMED",
  "TRANSP": "OPAQUE",
  "X-APPLE-TRAVEL-ADVISORY-BEHAVService37 ": "AUTOMATIC",
  "XCALNAME": "0C4F428B-BF4B-43DA-BEC3-510AA178728C"
 },
 {
  "SUMMARY": "#0152789: [Routine] Restore Users  Edge Services ",
  "DTSTART;TZID=US/Central": "20211018T223000",
  "DTEND;TZID=US/Central": "20211018T224500",
  "DTSTAMP;VALUE=DATE-TIME": "20211018T153000Z",
  "UID": "106C61B3-3483-4B82-8EEC-4735310E5E13",
  "SEQUENCE": "0",
  "CREATED;VALUE=DATE-TIME": "20211014T182011Z",
  "LAST-MODIFIED": "20211014T194550Z",
  "XCALNEW": "True",
  "STATUS": "CONFIRMED",
  "TRANSP": "OPAQUE",
  "X-APPLE-TRAVEL-ADVISORY-BEHAVService37 ": "AUTOMATIC",
  "XCALNAME": "106C61B3-3483-4B82-8EEC-4735310E5E13"
 },
 {
  "SUMMARY": "#0188102: [Routine] Update OS on license servers  ",
  "DTSTART;TZID=US/Central": "20211018T100000",
  "DTEND;TZID=US/Central": "20211018T110000",
  "DTSTAMP;VALUE=DATE-TIME": "20211018T153000Z",
  "UID": "121EA7BF-A3A7-4874-BBD9-7452D7E8C2B5",
  "SEQUENCE": "0",
  "CREATED;VALUE=DATE-TIME": "20211014T185630Z",
  "LAST-MODIFIED": "20211014T190126Z",
  "XCALNEW": "True",
  "STATUS": "CONFIRMED",
  "TRANSP": "OPAQUE",
  "X-APPLE-TRAVEL-ADVISORY-BEHAVService37 ": "AUTOMATIC",
  "XCALNAME": "121EA7BF-A3A7-4874-BBD9-7452D7E8C2B5"
 },
 {
  "SUMMARY": "#0186131: install libtinfo v5 and rlang on computes ",
  "DTSTART;TZID=US/Central": "20211018T110000",
  "DTEND;TZID=US/Central": "20211018T120000",
  "DTSTAMP": "20211014T191525Z",
  "UID": "17E9F8D4-0382-4AEE-BA10-0C5E00922B96",
  "SEQUENCE": "0",
  "CREATED": "20211014T182012Z",
  "LAST-MODIFIED": "20211014T191525Z",
  "STATUS": "CONFIRMED",
  "TRANSP": "OPAQUE",
  "X-APPLE-TRAVEL-ADVISORY-BEHAVService37 ": "AUTOMATIC",
  "XCALNAME": "17E9F8D4-0382-4AEE-BA10-0C5E00922B96.ics"
 },
 {
  "SUMMARY": "#0184696: System71  OS 5.1 testing ",
  "DTSTART;TZID=US/Central": "20211018T120000",
  "DTEND;TZID=US/Central": "20211018T200000",
  "DTSTAMP;VALUE=DATE-TIME": "20211018T203000Z",
  "UID": "1F55EB67-AF5A-49BA-8FB8-EF6FC8447BE4",
  "SEQUENCE": "0",
  "CREATED;VALUE=DATE-TIME": "20211014T182012Z",
  "LAST-MODIFIED": "20211014T191459Z",
  "XCALNEW": "True",
  "STATUS": "CONFIRMED",
  "TRANSP": "OPAQUE",
  "X-APPLE-TRAVEL-ADVISORY-BEHAVService37 ": "AUTOMATIC",
  "XCALNAME": "1F55EB67-AF5A-49BA-8FB8-EF6FC8447BE4"
 },
 {
  "SUMMARY": "#0143798: [Routine] [System3 ]  Restore Users  Project1  CI environment ",
  "DTSTART;TZID=US/Central": "20211018T230000",
  "DTEND;TZID=US/Central": "20211018T233000",
  "DTSTAMP;VALUE=DATE-TIME": "20211018T183000Z",
  "UID": "2140E28C-D55E-4067-A88E-421FB6F66D49",
  "SEQUENCE": "0",
  "CREATED;VALUE=DATE-TIME": "20211014T182011Z",
  "LAST-MODIFIED": "20211014T193153Z",
  "XCALNEW": "True",
  "STATUS": "CONFIRMED",
  "TRANSP": "OPAQUE",
  "X-APPLE-TRAVEL-ADVISORY-BEHAVService37 ": "AUTOMATIC",
  "XCALNAME": "2140E28C-D55E-4067-A88E-421FB6F66D49"
 },
 {
  "SUMMARY": "System4 DataNode04 card swap",
  "DTSTART;TZID=America/Chicago": "20211018T110000",
  "DTEND;TZID=America/Chicago": "20211018T120000",
  "DTSTAMP": "20211014T194244Z",
  "UID": "389454CC-83E4-4223-A31B-183CAC02246C",
  "SEQUENCE": "1",
  "CREATED": "20211014T193944Z",
  "LAST-MODIFIED": "20211014T194017Z",
  "TRANSP": "OPAQUE",
  "X-APPLE-TRAVEL-ADVISORY-BEHAVService37 ": "AUTOMATIC",
  "XCALNAME": "389454CC-83E4-4223-A31B-183CAC02246C.ics"
 },
 {
  "SUMMARY": "#0182157: System3 : Update Service55  Service34  node list  ",
  "DTSTART;TZID=US/Central": "20211018T163000",
  "DTEND;TZID=US/Central": "20211018T170000",
  "DTSTAMP;VALUE=DATE-TIME": "20211018T213000Z",
  "UID": "3DCB5043-9345-4E27-8909-7A951CDA2E2C",
  "SEQUENCE": "0",
  "CREATED;VALUE=DATE-TIME": "20211014T182012Z",
  "LAST-MODIFIED": "20211014T191656Z",
  "XCALNEW": "True",
  "STATUS": "CONFIRMED",
  "TRANSP": "OPAQUE",
  "X-APPLE-TRAVEL-ADVISORY-BEHAVService37 ": "AUTOMATIC",
  "XCALNAME": "3DCB5043-9345-4E27-8909-7A951CDA2E2C"
 },
 {
  "SUMMARY": "#0146392:  Kick Users  Service27  ",
  "DTSTART;TZID=US/Central": "20211018T090000",
  "DTEND;TZID=US/Central": "20211018T091500",
  "DTSTAMP;VALUE=DATE-TIME": "20211018T183000Z",
  "UID": "44421A33-DA70-4297-ADFA-A5A61E708F11",
  "SEQUENCE": "0",
  "CREATED;VALUE=DATE-TIME": "20211014T182011Z",
  "LAST-MODIFIED": "20211014T182409Z",
  "XCALNEW": "True",
  "STATUS": "CONFIRMED",
  "TRANSP": "OPAQUE",
  "X-APPLE-TRAVEL-ADVISORY-BEHAVService37 ": "AUTOMATIC",
  "XCALNAME": "44421A33-DA70-4297-ADFA-A5A61E708F11"
 },
 {
  "SUMMARY": " Restore Users /Release System3  ",
  "DTSTART;TZID=US/Central": "20211018T223000",
  "DTEND;TZID=US/Central": "20211018T230000",
  "DTSTAMP;VALUE=DATE-TIME": "20211019T023000Z",
  "UID": "493EF48C-FB1B-4FD7-88CB-6ADDDCF7E30A",
  "SEQUENCE": "0",
  "CREATED;VALUE=DATE-TIME": "20211014T182012Z",
  "LAST-MODIFIED": "20211014T194518Z",
  "XCALNEW": "True",
  "STATUS": "CONFIRMED",
  "TRANSP": "OPAQUE",
  "X-APPLE-TRAVEL-ADVISORY-BEHAVService37 ": "AUTOMATIC",
  "XCALNAME": "493EF48C-FB1B-4FD7-88CB-6ADDDCF7E30A"
 },
 {
  "SUMMARY": " Restore Users /Release System2  ",
  "DTSTART;TZID=US/Central": "20211018T223000",
  "DTEND;TZID=US/Central": "20211018T230000",
  "DTSTAMP;VALUE=DATE-TIME": "20211019T023000Z",
  "UID": "4F99FEFA-6BB4-456A-8802-BB730B74E077",
  "SEQUENCE": "0",
  "CREATED;VALUE=DATE-TIME": "20211014T182012Z",
  "LAST-MODIFIED": "20211014T194507Z",
  "XCALNEW": "True",
  "STATUS": "CONFIRMED",
  "TRANSP": "OPAQUE",
  "X-APPLE-TRAVEL-ADVISORY-BEHAVService37 ": "AUTOMATIC",
  "XCALNAME": "4F99FEFA-6BB4-456A-8802-BB730B74E077"
 },
 {
  "SUMMARY": "#0151640: [Routine] Restore Users  Service27  ",
  "DTSTART;TZID=US/Central": "20211018T223000",
  "DTEND;TZID=US/Central": "20211018T224500",
  "DTSTAMP;VALUE=DATE-TIME": "20211018T163000Z",
  "UID": "51084FD7-4074-4C84-893F-3395FEEAE548",
  "SEQUENCE": "0",
  "CREATED;VALUE=DATE-TIME": "20211014T182011Z",
  "LAST-MODIFIED": "20211014T194607Z",
  "XCALNEW": "True",
  "STATUS": "CONFIRMED",
  "TRANSP": "OPAQUE",
  "X-APPLE-TRAVEL-ADVISORY-BEHAVService37 ": "AUTOMATIC",
  "XCALNAME": "51084FD7-4074-4C84-893F-3395FEEAE548"
 },
 {
  "SUMMARY": "#0145866:  Kick Users  DataNodes  ",
  "DTSTART;TZID=US/Central": "20211018T090000",
  "DTEND;TZID=US/Central": "20211018T093000",
  "DTSTAMP;VALUE=DATE-TIME": "20211019T003000Z",
  "UID": "566B7F84-C28D-48F9-AB68-9D4C3E278D6D",
  "SEQUENCE": "0",
  "CREATED;VALUE=DATE-TIME": "20211014T182012Z",
  "LAST-MODIFIED": "20211014T183735Z",
  "XCALNEW": "True",
  "STATUS": "CONFIRMED",
  "TRANSP": "OPAQUE",
  "X-APPLE-TRAVEL-ADVISORY-BEHAVService37 ": "AUTOMATIC",
  "XCALNAME": "566B7F84-C28D-48F9-AB68-9D4C3E278D6D"
 },
 {
  "SUMMARY": "#0129711: [Routine] [System3 ] Rebuild Images ",
  "DTSTART;TZID=US/Central": "20211018T150000",
  "DTEND;TZID=US/Central": "20211018T170000",
  "DTSTAMP;VALUE=DATE-TIME": "20211018T203000Z",
  "UID": "56D3E882-3CB0-45FE-A11F-686961AA7E79",
  "SEQUENCE": "0",
  "CREATED;VALUE=DATE-TIME": "20211014T182012Z",
  "LAST-MODIFIED": "20211014T183702Z",
  "XCALNEW": "True",
  "STATUS": "CONFIRMED",
  "TRANSP": "OPAQUE",
  "X-APPLE-TRAVEL-ADVISORY-BEHAVService37 ": "AUTOMATIC",
  "XCALNAME": "56D3E882-3CB0-45FE-A11F-686961AA7E79"
 },
 {
  "SUMMARY": "#0184680: OS Patch Edge Services ",
  "DTSTART;TZID=US/Central": "20211018T100000",
  "DTEND;TZID=US/Central": "20211018T120000",
  "DTSTAMP;VALUE=DATE-TIME": "20211018T233000Z",
  "UID": "5D563CFA-16FF-445E-BE86-16016A6538C8",
  "SEQUENCE": "0",
  "CREATED;VALUE=DATE-TIME": "20211014T182012Z",
  "LAST-MODIFIED": "20211014T183403Z",
  "XCALNEW": "True",
  "STATUS": "CONFIRMED",
  "TRANSP": "OPAQUE",
  "X-APPLE-TRAVEL-ADVISORY-BEHAVService37 ": "AUTOMATIC",
  "XCALNAME": "5D563CFA-16FF-445E-BE86-16016A6538C8"
 },
 {
  "SUMMARY": "#0157265: [Routine] [System3 ] Reboot System3  ",
  "DTSTART;TZID=US/Central": "20211018T170000",
  "DTEND;TZID=US/Central": "20211018T200000",
  "DTSTAMP;VALUE=DATE-TIME": "20211018T183000Z",
  "UID": "6152F3C9-71E4-46D7-9335-02F28E23FE5C",
  "SEQUENCE": "0",
  "CREATED;VALUE=DATE-TIME": "20211014T182011Z",
  "LAST-MODIFIED": "20211014T182722Z",
  "XCALNEW": "True",
  "STATUS": "CONFIRMED",
  "TRANSP": "OPAQUE",
  "X-APPLE-TRAVEL-ADVISORY-BEHAVService37 ": "AUTOMATIC",
  "XCALNAME": "6152F3C9-71E4-46D7-9335-02F28E23FE5C"
 },
 {
  "SUMMARY": "System2  Pre-Release testing ",
  "DTSTART;TZID=US/Central": "20211018T203000",
  "DTEND;TZID=US/Central": "20211018T223000",
  "DTSTAMP;VALUE=DATE-TIME": "20211019T003000Z",
  "UID": "688D4980-5D98-4F07-9E50-8194A5AEEF81",
  "SEQUENCE": "0",
  "CREATED;VALUE=DATE-TIME": "20211014T182012Z",
  "LAST-MODIFIED": "20211014T194417Z",
  "XCALNEW": "True",
  "STATUS": "CONFIRMED",
  "TRANSP": "OPAQUE",
  "X-APPLE-TRAVEL-ADVISORY-BEHAVService37 ": "AUTOMATIC",
  "XCALNAME": "688D4980-5D98-4F07-9E50-8194A5AEEF81"
 },
 {
  "SUMMARY": "#0184695: Switch to new Service45 /Service64  server ",
  "DTSTART;TZID=US/Central": "20211018T140000",
  "DTEND;TZID=US/Central": "20211018T160000",
  "DTSTAMP;VALUE=DATE-TIME": "20211018T203000Z",
  "UID": "72B8D542-4D27-43B4-BBF3-59B3E186613A",
  "SEQUENCE": "0",
  "CREATED;VALUE=DATE-TIME": "20211014T182012Z",
  "LAST-MODIFIED": "20211014T183205Z",
  "XCALNEW": "True",
  "STATUS": "CONFIRMED",
  "TRANSP": "OPAQUE",
  "X-APPLE-TRAVEL-ADVISORY-BEHAVService37 ": "AUTOMATIC",
  "XCALNAME": "72B8D542-4D27-43B4-BBF3-59B3E186613A"
 },
 {
  "SUMMARY": "#0188038: System18  Network config verfiy ",
  "DTSTART;TZID=US/Central": "20211018T110000",
  "DTEND;TZID=US/Central": "20211018T120000",
  "DTSTAMP;VALUE=DATE-TIME": "20211018T173000Z",
  "UID": "74A7247B-B341-40F8-BDEF-CF67D07747F9",
  "SEQUENCE": "0",
  "CREATED;VALUE=DATE-TIME": "20211014T182011Z",
  "LAST-MODIFIED": "20211014T183839Z",
  "XCALNEW": "True",
  "STATUS": "CONFIRMED",
  "TRANSP": "OPAQUE",
  "X-APPLE-TRAVEL-ADVISORY-BEHAVService37 ": "AUTOMATIC",
  "XCALNAME": "74A7247B-B341-40F8-BDEF-CF67D07747F9"
 },
 {
  "SUMMARY": "#0152790: [Routine]  Kick Users  Edge Services ",
  "DTSTART;TZID=US/Central": "20211018T090000",
  "DTEND;TZID=US/Central": "20211018T091500",
  "DTSTAMP;VALUE=DATE-TIME": "20211018T163000Z",
  "UID": "752C7C52-AA3F-4885-9BC2-9880FF6BAC63",
  "SEQUENCE": "0",
  "CREATED;VALUE=DATE-TIME": "20211014T182011Z",
  "LAST-MODIFIED": "20211014T182323Z",
  "XCALNEW": "True",
  "STATUS": "CONFIRMED",
  "TRANSP": "OPAQUE",
  "X-APPLE-TRAVEL-ADVISORY-BEHAVService37 ": "AUTOMATIC",
  "XCALNAME": "752C7C52-AA3F-4885-9BC2-9880FF6BAC63"
 },
 {
  "SUMMARY": "#0143796: [Routine] [System3 ]  Kick Users  Project1  CI environment ",
  "DTSTART;TZID=US/Central": "20211018T084500",
  "DTEND;TZID=US/Central": "20211018T090000",
  "DTSTAMP;VALUE=DATE-TIME": "20211018T163000Z",
  "UID": "792E17F2-4E0D-43FE-ACE0-A33DE9188401",
  "SEQUENCE": "0",
  "CREATED;VALUE=DATE-TIME": "20211014T182011Z",
  "LAST-MODIFIED": "20211014T184051Z",
  "XCALNEW": "True",
  "STATUS": "CONFIRMED",
  "TRANSP": "OPAQUE",
  "X-APPLE-TRAVEL-ADVISORY-BEHAVService37 ": "AUTOMATIC",
  "XCALNAME": "792E17F2-4E0D-43FE-ACE0-A33DE9188401"
 },
 {
  "SUMMARY": "#0129715: [Routine][System3 ] Unmount Filesystems [Service55 \\,Service23 ] ",
  "DTSTART;TZID=US/Central": "20211018T093000",
  "DTEND;TZID=US/Central": "20211018T100000",
  "DTSTAMP;VALUE=DATE-TIME": "20211018T223000Z",
  "UID": "7B69FF74-AE1A-475F-81DE-1A7190E94F5C",
  "SEQUENCE": "0",
  "CREATED;VALUE=DATE-TIME": "20211014T182012Z",
  "LAST-MODIFIED": "20211014T182743Z",
  "XCALNEW": "True",
  "STATUS": "CONFIRMED",
  "TRANSP": "OPAQUE",
  "X-APPLE-TRAVEL-ADVISORY-BEHAVService37 ": "AUTOMATIC",
  "XCALNAME": "7B69FF74-AE1A-475F-81DE-1A7190E94F5C"
 },
 {
  "SUMMARY": " Restore Users /Release System5  ",
  "DTSTART;TZID=US/Central": "20211018T173000",
  "DTEND;TZID=US/Central": "20211018T180000",
  "DTSTAMP;VALUE=DATE-TIME": "20211019T023000Z",
  "UID": "82B6AD73-C74D-4313-9B87-2CD416997FBD",
  "SEQUENCE": "0",
  "CREATED;VALUE=DATE-TIME": "20211014T182012Z",
  "LAST-MODIFIED": "20211014T192844Z",
  "XCALNEW": "True",
  "STATUS": "CONFIRMED",
  "TRANSP": "OPAQUE",
  "X-APPLE-TRAVEL-ADVISORY-BEHAVService37 ": "AUTOMATIC",
  "XCALNAME": "82B6AD73-C74D-4313-9B87-2CD416997FBD"
 },
 {
  "SUMMARY": " Kick Users  System5  ",
  "DTSTART;TZID=US/Central;VALUE=DATE-TIME": "20211018T090000",
  "DTEND;TZID=US/Central;VALUE=DATE-TIME": "20211018T093000",
  "DTSTAMP;VALUE=DATE-TIME": "20211018T150000Z",
  "UID": "855A34BA-0104-4F0C-B7A1-7018A780B56F",
  "SEQUENCE": "0",
  "CREATED;VALUE=DATE-TIME": "20211014T182011Z",
  "LAST-MODIFIED": "20211014T183947Z",
  "XCALNEW": "True",
  "STATUS": "CONFIRMED",
  "TRANSP": "OPAQUE",
  "X-APPLE-TRAVEL-ADVISORY-BEHAVService37 ": "AUTOMATIC",
  "XCALNAME": "855A34BA-0104-4F0C-B7A1-7018A780B56F"
 },
 {
  "SUMMARY": "#0186288: [PM] Run Service37 /mdtest benchmarks on System2   ",
  "DTSTART;TZID=US/Central": "20211018T113000",
  "DTEND;TZID=US/Central": "20211018T153000",
  "DTSTAMP;VALUE=DATE-TIME": "20211018T233000Z",
  "UID": "96D26CFA-7D77-46C2-A59E-EE6D11BC44CB",
  "SEQUENCE": "0",
  "CREATED;VALUE=DATE-TIME": "20211014T182012Z",
  "LAST-MODIFIED": "20211014T192024Z",
  "XCALNEW": "True",
  "STATUS": "CONFIRMED",
  "TRANSP": "OPAQUE",
  "X-APPLE-TRAVEL-ADVISORY-BEHAVService37 ": "AUTOMATIC",
  "XCALNAME": "96D26CFA-7D77-46C2-A59E-EE6D11BC44CB"
 },
 {
  "SUMMARY": "#0146393:  Restore Users  Service27  ",
  "DTSTART;TZID=US/Central": "20211018T223000",
  "DTEND;TZID=US/Central": "20211018T230000",
  "DTSTAMP;VALUE=DATE-TIME": "20211018T213000Z",
  "UID": "A18F122D-F19C-4A08-B37B-4D2410F53195",
  "SEQUENCE": "0",
  "CREATED;VALUE=DATE-TIME": "20211014T182012Z",
  "LAST-MODIFIED": "20211014T194533Z",
  "XCALNEW": "True",
  "STATUS": "CONFIRMED",
  "TRANSP": "OPAQUE",
  "X-APPLE-TRAVEL-ADVISORY-BEHAVService37 ": "AUTOMATIC",
  "XCALNAME": "A18F122D-F19C-4A08-B37B-4D2410F53195"
 },
 {
  "SUMMARY": "#0188037: Deploy Service27  System2  ",
  "DTSTART;TZID=US/Central": "20211018T130000",
  "DTEND;TZID=US/Central": "20211018T140000",
  "DTSTAMP;VALUE=DATE-TIME": "20211018T183000Z",
  "UID": "A1F86670-6089-4A88-900D-A6EFB8CD7AF7",
  "SEQUENCE": "0",
  "CREATED;VALUE=DATE-TIME": "20211014T182012Z",
  "LAST-MODIFIED": "20211014T184018Z",
  "XCALNEW": "True",
  "STATUS": "CONFIRMED",
  "TRANSP": "OPAQUE",
  "X-APPLE-TRAVEL-ADVISORY-BEHAVService37 ": "AUTOMATIC",
  "XCALNAME": "A1F86670-6089-4A88-900D-A6EFB8CD7AF7"
 },
 {
  "SUMMARY": " Kick Users  System2  ",
  "DTSTART;TZID=US/Central;VALUE=DATE-TIME": "20211018T090000",
  "DTEND;TZID=US/Central;VALUE=DATE-TIME": "20211018T093000",
  "DTSTAMP;VALUE=DATE-TIME": "20211018T150000Z",
  "UID": "A803E785-A35D-4FD2-8169-755BF462767A",
  "SEQUENCE": "0",
  "CREATED;VALUE=DATE-TIME": "20211014T182011Z",
  "LAST-MODIFIED": "20211014T183902Z",
  "XCALNEW": "True",
  "STATUS": "CONFIRMED",
  "TRANSP": "OPAQUE",
  "X-APPLE-TRAVEL-ADVISORY-BEHAVService37 ": "AUTOMATIC",
  "XCALNAME": "A803E785-A35D-4FD2-8169-755BF462767A"
 },
 {
  "SUMMARY": "#0129716: [Routine] [System3 ] Remount Filesystems [Service55 \\,Service23 ] ",
  "DTSTART;TZID=US/Central": "20211018T200000",
  "DTEND;TZID=US/Central": "20211018T203000",
  "DTSTAMP;VALUE=DATE-TIME": "20211018T203000Z",
  "UID": "A916C0F5-799E-4492-A667-0ADA1987F986",
  "SEQUENCE": "0",
  "CREATED;VALUE=DATE-TIME": "20211014T182012Z",
  "LAST-MODIFIED": "20211014T192748Z",
  "XCALNEW": "True",
  "STATUS": "CONFIRMED",
  "TRANSP": "OPAQUE",
  "X-APPLE-TRAVEL-ADVISORY-BEHAVService37 ": "AUTOMATIC",
  "XCALNAME": "A916C0F5-799E-4492-A667-0ADA1987F986"
 },
 {
  "SUMMARY": "#0168690: [Routine] [System6 \\, System7 \\, System8 ] Remount Service55  filesystems ",
  "DTSTART;TZID=US/Central": "20211018T153000",
  "DTEND;TZID=US/Central": "20211018T163000",
  "DTSTAMP;VALUE=DATE-TIME": "20211018T223000Z",
  "UID": "AE144702-70E1-4883-9E74-88071EE8798D",
  "SEQUENCE": "0",
  "CREATED;VALUE=DATE-TIME": "20211014T182012Z",
  "LAST-MODIFIED": "20211014T192620Z",
  "XCALNEW": "True",
  "STATUS": "CONFIRMED",
  "TRANSP": "OPAQUE",
  "X-APPLE-TRAVEL-ADVISORY-BEHAVService37 ": "AUTOMATIC",
  "XCALNAME": "AE144702-70E1-4883-9E74-88071EE8798D"
 },
 {
  "SUMMARY": "#0188068: Service34  cable replacement on System6  and System7  ",
  "DTSTART;TZID=US/Central": "20211018T103000",
  "DTEND;TZID=US/Central": "20211018T153000",
  "DTSTAMP;VALUE=DATE-TIME": "20211018T213000Z",
  "UID": "B2F7E0BE-2EA1-4B67-976B-F025B699E265",
  "SEQUENCE": "0",
  "CREATED;VALUE=DATE-TIME": "20211014T182012Z",
  "LAST-MODIFIED": "20211014T191104Z",
  "XCALNEW": "True",
  "STATUS": "CONFIRMED",
  "TRANSP": "OPAQUE",
  "X-APPLE-TRAVEL-ADVISORY-BEHAVService37 ": "AUTOMATIC",
  "XCALNAME": "B2F7E0BE-2EA1-4B67-976B-F025B699E265"
 },
 {
  "SUMMARY": "#0168689: [Routine] [System6 \\, System7 \\, System8 ] Unmount Service23  filesystems for PM ",
  "DTSTART;TZID=US/Central": "20211018T100000",
  "DTEND;TZID=US/Central": "20211018T110000",
  "DTSTAMP;VALUE=DATE-TIME": "20211018T193000Z",
  "UID": "BDAE5BB5-BF9A-44EB-85FC-69FB06CFCA03",
  "SEQUENCE": "0",
  "CREATED;VALUE=DATE-TIME": "20211014T182012Z",
  "LAST-MODIFIED": "20211014T190439Z",
  "XCALNEW": "True",
  "STATUS": "CONFIRMED",
  "TRANSP": "OPAQUE",
  "X-APPLE-TRAVEL-ADVISORY-BEHAVService37 ": "AUTOMATIC",
  "XCALNAME": "BDAE5BB5-BF9A-44EB-85FC-69FB06CFCA03"
 },
 {
  "SUMMARY": "#0184667: Patch OS for  web servers ",
  "DTSTART;TZID=US/Central": "20211018T140000",
  "DTEND;TZID=US/Central": "20211018T150000",
  "DTSTAMP;VALUE=DATE-TIME": "20211018T153000Z",
  "UID": "BF59C92D-D9DC-46AF-990E-66138FF306D6",
  "SEQUENCE": "0",
  "CREATED;VALUE=DATE-TIME": "20211014T182011Z",
  "LAST-MODIFIED": "20211014T184147Z",
  "XCALNEW": "True",
  "STATUS": "CONFIRMED",
  "TRANSP": "OPAQUE",
  "X-APPLE-TRAVEL-ADVISORY-BEHAVService37 ": "AUTOMATIC",
  "XCALNAME": "BF59C92D-D9DC-46AF-990E-66138FF306D6"
 },
 {
  "SUMMARY": "#0129708: [Routine][System3 ] XC Hardware Replacement ",
  "DTSTART;TZID=US/Central": "20211018T100000",
  "DTEND;TZID=US/Central": "20211018T150000",
  "DTSTAMP;VALUE=DATE-TIME": "20211018T193000Z",
  "UID": "CC5789E7-87ED-4D98-95A4-32737F07FC62",
  "SEQUENCE": "0",
  "CREATED;VALUE=DATE-TIME": "20211014T182012Z",
  "LAST-MODIFIED": "20211014T183226Z",
  "XCALNEW": "True",
  "STATUS": "CONFIRMED",
  "TRANSP": "OPAQUE",
  "X-APPLE-TRAVEL-ADVISORY-BEHAVService37 ": "AUTOMATIC",
  "XCALNAME": "CC5789E7-87ED-4D98-95A4-32737F07FC62"
 },
 {
  "SUMMARY": "#0188056: RHEL userland updates on DataNodes  ",
  "DTSTART;TZID=US/Central": "20211018T130000",
  "DTEND;TZID=US/Central": "20211018T140000",
  "DTSTAMP;VALUE=DATE-TIME": "20211018T233000Z",
  "UID": "D37DE4F2-3E98-41D8-A1AA-D6A009A21F86",
  "SEQUENCE": "0",
  "CREATED;VALUE=DATE-TIME": "20211014T182012Z",
  "LAST-MODIFIED": "20211014T183147Z",
  "XCALNEW": "True",
  "STATUS": "CONFIRMED",
  "TRANSP": "OPAQUE",
  "X-APPLE-TRAVEL-ADVISORY-BEHAVService37 ": "AUTOMATIC",
  "XCALNAME": "D37DE4F2-3E98-41D8-A1AA-D6A009A21F86"
 },
 {
  "SUMMARY": "#0145867: [Routine]  Restore Users  DataNodes ",
  "DTSTART;TZID=US/Central": "20211018T173000",
  "DTEND;TZID=US/Central": "20211018T180000",
  "DTSTAMP;VALUE=DATE-TIME": "20211018T213000Z",
  "UID": "D60E41FD-19AD-46EF-AC26-277851DB09D9",
  "SEQUENCE": "0",
  "CREATED;VALUE=DATE-TIME": "20211014T182012Z",
  "LAST-MODIFIED": "20211014T193132Z",
  "XCALNEW": "True",
  "STATUS": "CONFIRMED",
  "TRANSP": "OPAQUE",
  "X-APPLE-TRAVEL-ADVISORY-BEHAVService37 ": "AUTOMATIC",
  "XCALNAME": "D60E41FD-19AD-46EF-AC26-277851DB09D9"
 },
 {
  "SUMMARY": "#0186285: System3  PE 21.09 Install  ",
  "DTSTART;TZID=US/Central": "20211018T100000",
  "DTEND;TZID=US/Central": "20211018T130000",
  "DTSTAMP;VALUE=DATE-TIME": "20211018T193000Z",
  "UID": "DEDFAE3B-C7A0-47DB-B89E-C8F2A49DE932",
  "SEQUENCE": "0",
  "CREATED;VALUE=DATE-TIME": "20211014T182012Z",
  "LAST-MODIFIED": "20211014T191219Z",
  "XCALNEW": "True",
  "STATUS": "CONFIRMED",
  "TRANSP": "OPAQUE",
  "X-APPLE-TRAVEL-ADVISORY-BEHAVService37 ": "AUTOMATIC",
  "XCALNAME": "DEDFAE3B-C7A0-47DB-B89E-C8F2A49DE932"
 },
 {
  "SUMMARY": "System5  Pre-Release testing ",
  "DTSTART;TZID=US/Central": "20211018T153000",
  "DTEND;TZID=US/Central": "20211018T173000",
  "DTSTAMP;VALUE=DATE-TIME": "20211019T003000Z",
  "UID": "E376C72F-727D-4F40-BCD1-2BF4814131EB",
  "SEQUENCE": "0",
  "CREATED;VALUE=DATE-TIME": "20211014T182012Z",
  "LAST-MODIFIED": "20211014T192645Z",
  "XCALNEW": "True",
  "STATUS": "CONFIRMED",
  "TRANSP": "OPAQUE",
  "X-APPLE-TRAVEL-ADVISORY-BEHAVService37 ": "AUTOMATIC",
  "XCALNAME": "E376C72F-727D-4F40-BCD1-2BF4814131EB"
 },
 {
  "SUMMARY": "System3  Pre-Release testing ",
  "DTSTART;TZID=US/Central": "20211018T203000",
  "DTEND;TZID=US/Central": "20211018T223000",
  "DTSTAMP;VALUE=DATE-TIME": "20211019T003000Z",
  "UID": "E77AD701-F6CB-45B1-8EDA-2D2985F6CD43",
  "SEQUENCE": "0",
  "CREATED;VALUE=DATE-TIME": "20211014T182012Z",
  "LAST-MODIFIED": "20211014T194450Z",
  "XCALNEW": "True",
  "STATUS": "CONFIRMED",
  "TRANSP": "OPAQUE",
  "X-APPLE-TRAVEL-ADVISORY-BEHAVService37 ": "AUTOMATIC",
  "XCALNAME": "E77AD701-F6CB-45B1-8EDA-2D2985F6CD43"
 },
 {
  "SUMMARY": "#0182065: Service40 -runner Service42  config System3  ",
  "DTSTART;TZID=US/Central": "20211018T170000",
  "DTEND;TZID=US/Central": "20211018T183000",
  "DTSTAMP;VALUE=DATE-TIME": "20211018T223000Z",
  "UID": "E7BAF419-B64A-422D-A3A9-E748124E7046",
  "SEQUENCE": "0",
  "CREATED;VALUE=DATE-TIME": "20211014T182012Z",
  "LAST-MODIFIED": "20211014T191747Z",
  "XCALNEW": "True",
  "STATUS": "CONFIRMED",
  "TRANSP": "OPAQUE",
  "X-APPLE-TRAVEL-ADVISORY-BEHAVService37 ": "AUTOMATIC",
  "XCALNAME": "E7BAF419-B64A-422D-A3A9-E748124E7046"
 },
 {
  "SUMMARY": " Kick Users  System3  ",
  "DTSTART;TZID=US/Central;VALUE=DATE-TIME": "20211018T090000",
  "DTEND;TZID=US/Central;VALUE=DATE-TIME": "20211018T093000",
  "DTSTAMP;VALUE=DATE-TIME": "20211018T150000Z",
  "UID": "FCDAE6E7-2A5F-4D0D-ACA3-C309C0301E70",
  "SEQUENCE": "0",
  "CREATED;VALUE=DATE-TIME": "20211014T182011Z",
  "LAST-MODIFIED": "20211014T184748Z",
  "XCALNEW": "True",
  "STATUS": "CONFIRMED",
  "TRANSP": "OPAQUE",
  "X-APPLE-TRAVEL-ADVISORY-BEHAVService37 ": "AUTOMATIC",
  "XCALNAME": "FCDAE6E7-2A5F-4D0D-ACA3-C309C0301E70"
 }
]